refstis/SignStsciRequest.py
refstis/__init__.py
refstis/basedark.py
refstis/basejoint.py
refstis/delivery.py
refstis/functions.py
refstis/iutil.py
refstis/msarith.py
refstis/pipeline.py
refstis/pop_db.py
refstis/refbias.py
refstis/retrieval.py
refstis/weekbias.py
refstis/weekdark.py
refstis-0.8.2.data/scripts/basedark
refstis-0.8.2.data/scripts/basejoint
refstis-0.8.2.data/scripts/refbias
refstis-0.8.2.data/scripts/refstis_pipeline
refstis-0.8.2.data/scripts/weekbias
refstis-0.8.2.data/scripts/weekdark
refstis-0.8.2.dist-info/LICENSE
refstis-0.8.2.dist-info/METADATA
refstis-0.8.2.dist-info/WHEEL
refstis-0.8.2.dist-info/top_level.txt
refstis-0.8.2.dist-info/RECORD
