Metadata-Version: 2.1
Name: refstis
Version: 0.8.2
Summary: Pipeline to create STIS CCD superdarks and superbiases
Home-page: https://refstis.readthedocs.io
Author: Allyssa Riley, Sean Lockwood, Justin Ely
Keywords: astronomy
Classifier: Programming Language :: Python :: 3
Classifier: Development Status :: 4 - Beta
Classifier: Intended Audience :: Science/Research
Classifier: Topic :: Scientific/Engineering :: Astronomy
Classifier: Topic :: Scientific/Engineering :: Physics
Classifier: Topic :: Software Development :: Libraries :: Python Modules
License-File: LICENSE
Requires-Dist: pyyaml
Requires-Dist: numpy
Requires-Dist: astropy >=3.1
Requires-Dist: stistools
